seqmat/__init__.py
seqmat/cli.py
seqmat/config.py
seqmat/gene.py
seqmat/lmdb_store.py
seqmat/seqmat.py
seqmat/transcript.py
seqmat/utils.py
seqmat-0.1.44.dist-info/licenses/LICENSE
tests/__init__.py
tests/test_gene.py
tests/test_lmdb.py
tests/test_seqmat.py
seqmat-0.1.44.dist-info/METADATA
seqmat-0.1.44.dist-info/WHEEL
seqmat-0.1.44.dist-info/entry_points.txt
seqmat-0.1.44.dist-info/top_level.txt
seqmat-0.1.44.dist-info/RECORD
