Metadata-Version: 2.4
Name: seqmat
Version: 0.1.44
Summary: Lightning-fast gene manipulation and analysis library.
Home-page: https://github.com/nicolasalynn/seqmat
Author: Nicolas Lynn Vila
Author-email: nicolasalynn@gmail.com
Classifier: Development Status :: 3 - Alpha
Classifier: Intended Audience :: Science/Research
Classifier: Topic :: Scientific/Engineering :: Bio-Informatics
Classifier: License :: OSI Approved :: MIT License
Classifier: Programming Language :: Python :: 3
Classifier: Programming Language :: Python :: 3.10
Classifier: Programming Language :: Python :: 3.11
Classifier: Programming Language :: Python :: 3.12
Requires-Python: >=3.10
License-File: LICENSE
Requires-Dist: numpy>=1.20.0
Requires-Dist: pandas>=2.0.0
Requires-Dist: pysam>=0.19.0
Requires-Dist: requests>=2.26.0
Requires-Dist: tqdm>=4.62.0
Requires-Dist: biopython>=1.79
Requires-Dist: gtfparse>=1.2.0
Requires-Dist: platformdirs>=3.0.0
Provides-Extra: lmdb
Requires-Dist: lmdb>=1.4.0; extra == "lmdb"
Provides-Extra: dev
Requires-Dist: pytest>=6.0; extra == "dev"
Requires-Dist: pytest-cov>=2.0; extra == "dev"
Requires-Dist: black>=21.0; extra == "dev"
Requires-Dist: flake8>=3.9; extra == "dev"
Requires-Dist: mypy>=0.910; extra == "dev"
Requires-Dist: lmdb>=1.4.0; extra == "dev"
Dynamic: author
Dynamic: author-email
Dynamic: classifier
Dynamic: description
Dynamic: description-content-type
Dynamic: home-page
Dynamic: license-file
Dynamic: provides-extra
Dynamic: requires-dist
Dynamic: requires-python
Dynamic: summary
